{
  "baseline": {
    "cases": {
      "calibrated": {
        "runs": [
          {
            "cost": 1199.1284207596611,
            "cov": 30,
            "shape": {
              "2": 30
            },
            "sig": "0256bf3d47c4",
            "time": 4.901785416
          }
        ],
        "summary": {
          "best": 1199.1284207596611,
          "cov": [
            30
          ],
          "mean": 1199.1284207596611,
          "ok": 1,
          "shapes": [
            "{\"2\": 30}"
          ],
          "sigs": [
            "0256bf3d47c4"
          ],
          "time": 4.901785416,
          "worst": 1199.1284207596611
        }
      },
      "large": {
        "runs": [
          {
            "cost": 657.1040208060375,
            "cov": 40,
            "shape": {
              "1": 3,
              "2": 34,
              "3": 3
            },
            "sig": "bbd61776be78",
            "time": 8.472750458
          }
        ],
        "summary": {
          "best": 657.1040208060375,
          "cov": [
            40
          ],
          "mean": 657.1040208060375,
          "ok": 1,
          "shapes": [
            "{\"1\": 3, \"2\": 34, \"3\": 3}"
          ],
          "sigs": [
            "bbd61776be78"
          ],
          "time": 8.472750458,
          "worst": 657.1040208060375
        }
      },
      "low025": {
        "runs": [
          {
            "cost": 1914.1994377442877,
            "cov": 30,
            "shape": {
              "3": 4,
              "4": 7,
              "5": 4
            },
            "sig": "627b18ab78be",
            "time": 8.78477375
          },
          {
            "cost": 1891.050799852403,
            "cov": 30,
            "shape": {
              "2": 1,
              "3": 3,
              "4": 6,
              "5": 5
            },
            "sig": "42c828e47d6b",
            "time": 8.793218084
          }
        ],
        "summary": {
          "best": 1891.050799852403,
          "cov": [
            30
          ],
          "mean": 1902.6251187983453,
          "ok": 2,
          "shapes": [
            "{\"2\": 1, \"3\": 3, \"4\": 6, \"5\": 5}",
            "{\"3\": 4, \"4\": 7, \"5\": 4}"
          ],
          "sigs": [
            "42c828e47d6b",
            "627b18ab78be"
          ],
          "time": 8.788995917,
          "worst": 1914.1994377442877
        }
      },
      "low030": {
        "runs": [
          {
            "cost": 1735.5042772053657,
            "cov": 30,
            "shape": {
              "2": 1,
              "3": 2,
              "4": 8,
              "5": 4
            },
            "sig": "bb3c54bb5868",
            "time": 9.012775874999999
          },
          {
            "cost": 1766.6942664281148,
            "cov": 30,
            "shape": {
              "2": 1,
              "3": 2,
              "4": 8,
              "5": 4
            },
            "sig": "b1271e8fb0f6",
            "time": 9.045792792
          }
        ],
        "summary": {
          "best": 1735.5042772053657,
          "cov": [
            30
          ],
          "mean": 1751.0992718167404,
          "ok": 2,
          "shapes": [
            "{\"2\": 1, \"3\": 2, \"4\": 8, \"5\": 4}"
          ],
          "sigs": [
            "b1271e8fb0f6",
            "bb3c54bb5868"
          ],
          "time": 9.0292843335,
          "worst": 1766.6942664281148
        }
      },
      "official_like": {
        "runs": [
          {
            "cost": 1616.75860162171,
            "cov": 30,
            "shape": {
              "1": 4,
              "2": 22,
              "3": 4
            },
            "sig": "55810f51c401",
            "time": 9.001442458
          },
          {
            "cost": 1616.75860162171,
            "cov": 30,
            "shape": {
              "1": 4,
              "2": 22,
              "3": 4
            },
            "sig": "55810f51c401",
            "time": 8.900248625
          }
        ],
        "summary": {
          "best": 1616.75860162171,
          "cov": [
            30
          ],
          "mean": 1616.75860162171,
          "ok": 2,
          "shapes": [
            "{\"1\": 4, \"2\": 22, \"3\": 4}"
          ],
          "sigs": [
            "55810f51c401"
          ],
          "time": 8.9508455415,
          "worst": 1616.75860162171
        }
      },
      "scarce40": {
        "runs": [
          {
            "cost": 1097.8470554,
            "cov": 40,
            "shape": {
              "1": 40
            },
            "sig": "2240d8d56f3b",
            "time": 12.965825500000001
          }
        ],
        "summary": {
          "best": 1097.8470554,
          "cov": [
            40
          ],
          "mean": 1097.8470554,
          "ok": 1,
          "shapes": [
            "{\"1\": 40}"
          ],
          "sigs": [
            "2240d8d56f3b"
          ],
          "time": 12.965825500000001,
          "worst": 1097.8470554
        }
      }
    },
    "sha": "70222083707d786011d28d7cc1ceab8f3b2ca95e0924b26f8dff2e6a49e865d6",
    "size": 78516
  },
  "rank_blend_low": {
    "cases": {
      "calibrated": {
        "runs": [
          {
            "cost": 1199.1284207596611,
            "cov": 30,
            "shape": {
              "2": 30
            },
            "sig": "0256bf3d47c4",
            "time": 4.752385917000001
          }
        ],
        "summary": {
          "best": 1199.1284207596611,
          "cov": [
            30
          ],
          "mean": 1199.1284207596611,
          "ok": 1,
          "shapes": [
            "{\"2\": 30}"
          ],
          "sigs": [
            "0256bf3d47c4"
          ],
          "time": 4.752385917000001,
          "worst": 1199.1284207596611
        }
      },
      "large": {
        "runs": [
          {
            "cost": 657.1040208060375,
            "cov": 40,
            "shape": {
              "1": 3,
              "2": 34,
              "3": 3
            },
            "sig": "bbd61776be78",
            "time": 7.987397791999999
          }
        ],
        "summary": {
          "best": 657.1040208060375,
          "cov": [
            40
          ],
          "mean": 657.1040208060375,
          "ok": 1,
          "shapes": [
            "{\"1\": 3, \"2\": 34, \"3\": 3}"
          ],
          "sigs": [
            "bbd61776be78"
          ],
          "time": 7.987397791999999,
          "worst": 657.1040208060375
        }
      },
      "low025": {
        "runs": [
          {
            "cost": 1914.1994377442877,
            "cov": 30,
            "shape": {
              "3": 4,
              "4": 7,
              "5": 4
            },
            "sig": "627b18ab78be",
            "time": 8.847931917
          },
          {
            "cost": 1922.1958991939941,
            "cov": 30,
            "shape": {
              "2": 1,
              "3": 2,
              "4": 8,
              "5": 4
            },
            "sig": "b1271e8fb0f6",
            "time": 9.434037958000001
          }
        ],
        "summary": {
          "best": 1914.1994377442877,
          "cov": [
            30
          ],
          "mean": 1918.1976684691408,
          "ok": 2,
          "shapes": [
            "{\"2\": 1, \"3\": 2, \"4\": 8, \"5\": 4}",
            "{\"3\": 4, \"4\": 7, \"5\": 4}"
          ],
          "sigs": [
            "627b18ab78be",
            "b1271e8fb0f6"
          ],
          "time": 9.1409849375,
          "worst": 1922.1958991939941
        }
      },
      "low030": {
        "runs": [
          {
            "cost": 1760.0074838412038,
            "cov": 30,
            "shape": {
              "3": 4,
              "4": 7,
              "5": 4
            },
            "sig": "2ec04b3dc23b",
            "time": 8.808964957999999
          },
          {
            "cost": 1766.6942664281148,
            "cov": 30,
            "shape": {
              "2": 1,
              "3": 2,
              "4": 8,
              "5": 4
            },
            "sig": "b1271e8fb0f6",
            "time": 9.097215540999999
          }
        ],
        "summary": {
          "best": 1760.0074838412038,
          "cov": [
            30
          ],
          "mean": 1763.3508751346594,
          "ok": 2,
          "shapes": [
            "{\"2\": 1, \"3\": 2, \"4\": 8, \"5\": 4}",
            "{\"3\": 4, \"4\": 7, \"5\": 4}"
          ],
          "sigs": [
            "2ec04b3dc23b",
            "b1271e8fb0f6"
          ],
          "time": 8.953090249499999,
          "worst": 1766.6942664281148
        }
      },
      "official_like": {
        "runs": [
          {
            "cost": 1616.7884665963338,
            "cov": 30,
            "shape": {
              "1": 5,
              "2": 20,
              "3": 5
            },
            "sig": "28fa9d86bbdf",
            "time": 8.991192792000001
          },
          {
            "cost": 1616.75860162171,
            "cov": 30,
            "shape": {
              "1": 4,
              "2": 22,
              "3": 4
            },
            "sig": "55810f51c401",
            "time": 9.170297375
          }
        ],
        "summary": {
          "best": 1616.75860162171,
          "cov": [
            30
          ],
          "mean": 1616.773534109022,
          "ok": 2,
          "shapes": [
            "{\"1\": 4, \"2\": 22, \"3\": 4}",
            "{\"1\": 5, \"2\": 20, \"3\": 5}"
          ],
          "sigs": [
            "28fa9d86bbdf",
            "55810f51c401"
          ],
          "time": 9.080745083500002,
          "worst": 1616.7884665963338
        }
      },
      "scarce40": {
        "runs": [
          {
            "cost": 1097.8470554,
            "cov": 40,
            "shape": {
              "1": 40
            },
            "sig": "2240d8d56f3b",
            "time": 16.557396584000003
          }
        ],
        "summary": {
          "best": 1097.8470554,
          "cov": [
            40
          ],
          "mean": 1097.8470554,
          "ok": 1,
          "shapes": [
            "{\"1\": 40}"
          ],
          "sigs": [
            "2240d8d56f3b"
          ],
          "time": 16.557396584000003,
          "worst": 1097.8470554
        }
      }
    },
    "sha": "9173a0f33d94f838e3db102a6c43a7bc91cf191e63028f1af3953942b67f7a90",
    "size": 78529
  },
  "rank_diverse_pool": {
    "cases": {
      "calibrated": {
        "runs": [
          {
            "cost": 1199.1284207596611,
            "cov": 30,
            "shape": {
              "2": 30
            },
            "sig": "0256bf3d47c4",
            "time": 4.783871208
          }
        ],
        "summary": {
          "best": 1199.1284207596611,
          "cov": [
            30
          ],
          "mean": 1199.1284207596611,
          "ok": 1,
          "shapes": [
            "{\"2\": 30}"
          ],
          "sigs": [
            "0256bf3d47c4"
          ],
          "time": 4.783871208,
          "worst": 1199.1284207596611
        }
      },
      "large": {
        "runs": [
          {
            "cost": 657.1040208060375,
            "cov": 40,
            "shape": {
              "1": 3,
              "2": 34,
              "3": 3
            },
            "sig": "bbd61776be78",
            "time": 8.554484875
          }
        ],
        "summary": {
          "best": 657.1040208060375,
          "cov": [
            40
          ],
          "mean": 657.1040208060375,
          "ok": 1,
          "shapes": [
            "{\"1\": 3, \"2\": 34, \"3\": 3}"
          ],
          "sigs": [
            "bbd61776be78"
          ],
          "time": 8.554484875,
          "worst": 657.1040208060375
        }
      },
      "low025": {
        "runs": [
          {
            "cost": 1922.1958991939941,
            "cov": 30,
            "shape": {
              "2": 1,
              "3": 2,
              "4": 8,
              "5": 4
            },
            "sig": "b1271e8fb0f6",
            "time": 8.879889333
          },
          {
            "cost": 1914.1994377442877,
            "cov": 30,
            "shape": {
              "3": 4,
              "4": 7,
              "5": 4
            },
            "sig": "627b18ab78be",
            "time": 8.936541875
          }
        ],
        "summary": {
          "best": 1914.1994377442877,
          "cov": [
            30
          ],
          "mean": 1918.1976684691408,
          "ok": 2,
          "shapes": [
            "{\"2\": 1, \"3\": 2, \"4\": 8, \"5\": 4}",
            "{\"3\": 4, \"4\": 7, \"5\": 4}"
          ],
          "sigs": [
            "627b18ab78be",
            "b1271e8fb0f6"
          ],
          "time": 8.908215603999999,
          "worst": 1922.1958991939941
        }
      },
      "low030": {
        "runs": [
          {
            "cost": 1766.6942664281148,
            "cov": 30,
            "shape": {
              "2": 1,
              "3": 2,
              "4": 8,
              "5": 4
            },
            "sig": "b1271e8fb0f6",
            "time": 9.001293708
          },
          {
            "cost": 1722.3753064465154,
            "cov": 30,
            "shape": {
              "2": 2,
              "3": 3,
              "4": 8,
              "5": 3
            },
            "sig": "652ab9186f09",
            "time": 8.899145208
          }
        ],
        "summary": {
          "best": 1722.3753064465154,
          "cov": [
            30
          ],
          "mean": 1744.5347864373152,
          "ok": 2,
          "shapes": [
            "{\"2\": 1, \"3\": 2, \"4\": 8, \"5\": 4}",
            "{\"2\": 2, \"3\": 3, \"4\": 8, \"5\": 3}"
          ],
          "sigs": [
            "652ab9186f09",
            "b1271e8fb0f6"
          ],
          "time": 8.950219458,
          "worst": 1766.6942664281148
        }
      },
      "official_like": {
        "runs": [
          {
            "cost": 1616.75860162171,
            "cov": 30,
            "shape": {
              "1": 4,
              "2": 22,
              "3": 4
            },
            "sig": "55810f51c401",
            "time": 9.242082583
          },
          {
            "cost": 1616.75860162171,
            "cov": 30,
            "shape": {
              "1": 4,
              "2": 22,
              "3": 4
            },
            "sig": "55810f51c401",
            "time": 8.985945791999999
          }
        ],
        "summary": {
          "best": 1616.75860162171,
          "cov": [
            30
          ],
          "mean": 1616.75860162171,
          "ok": 2,
          "shapes": [
            "{\"1\": 4, \"2\": 22, \"3\": 4}"
          ],
          "sigs": [
            "55810f51c401"
          ],
          "time": 9.1140141875,
          "worst": 1616.75860162171
        }
      },
      "scarce40": {
        "runs": [
          {
            "cost": 1090.9236368000002,
            "cov": 40,
            "shape": {
              "1": 39
            },
            "sig": "69f9b3c61a65",
            "time": 8.981255583
          }
        ],
        "summary": {
          "best": 1090.9236368000002,
          "cov": [
            40
          ],
          "mean": 1090.9236368000002,
          "ok": 1,
          "shapes": [
            "{\"1\": 39}"
          ],
          "sigs": [
            "69f9b3c61a65"
          ],
          "time": 8.981255583,
          "worst": 1090.9236368000002
        }
      }
    },
    "sha": "f444f0f381b5ecca6552148a422768988e53170a03bd8945a26ea610a13d621b",
    "size": 78613
  },
  "rank_score_only": {
    "cases": {
      "calibrated": {
        "runs": [
          {
            "cost": 1199.1284207596611,
            "cov": 30,
            "shape": {
              "2": 30
            },
            "sig": "0256bf3d47c4",
            "time": 4.681998417
          }
        ],
        "summary": {
          "best": 1199.1284207596611,
          "cov": [
            30
          ],
          "mean": 1199.1284207596611,
          "ok": 1,
          "shapes": [
            "{\"2\": 30}"
          ],
          "sigs": [
            "0256bf3d47c4"
          ],
          "time": 4.681998417,
          "worst": 1199.1284207596611
        }
      },
      "large": {
        "runs": [
          {
            "cost": 657.1040208060375,
            "cov": 40,
            "shape": {
              "1": 3,
              "2": 34,
              "3": 3
            },
            "sig": "bbd61776be78",
            "time": 7.690171042
          }
        ],
        "summary": {
          "best": 657.1040208060375,
          "cov": [
            40
          ],
          "mean": 657.1040208060375,
          "ok": 1,
          "shapes": [
            "{\"1\": 3, \"2\": 34, \"3\": 3}"
          ],
          "sigs": [
            "bbd61776be78"
          ],
          "time": 7.690171042,
          "worst": 657.1040208060375
        }
      },
      "low025": {
        "runs": [
          {
            "cost": 1891.050799852403,
            "cov": 30,
            "shape": {
              "2": 1,
              "3": 3,
              "4": 6,
              "5": 5
            },
            "sig": "42c828e47d6b",
            "time": 8.809698125
          },
          {
            "cost": 1891.050799852403,
            "cov": 30,
            "shape": {
              "2": 1,
              "3": 3,
              "4": 6,
              "5": 5
            },
            "sig": "42c828e47d6b",
            "time": 9.045114042
          }
        ],
        "summary": {
          "best": 1891.050799852403,
          "cov": [
            30
          ],
          "mean": 1891.050799852403,
          "ok": 2,
          "shapes": [
            "{\"2\": 1, \"3\": 3, \"4\": 6, \"5\": 5}"
          ],
          "sigs": [
            "42c828e47d6b"
          ],
          "time": 8.9274060835,
          "worst": 1891.050799852403
        }
      },
      "low030": {
        "runs": [
          {
            "cost": 1735.5042772053657,
            "cov": 30,
            "shape": {
              "2": 1,
              "3": 2,
              "4": 8,
              "5": 4
            },
            "sig": "bb3c54bb5868",
            "time": 8.989398833
          },
          {
            "cost": 1766.6942664281148,
            "cov": 30,
            "shape": {
              "2": 1,
              "3": 2,
              "4": 8,
              "5": 4
            },
            "sig": "b1271e8fb0f6",
            "time": 9.060260667
          }
        ],
        "summary": {
          "best": 1735.5042772053657,
          "cov": [
            30
          ],
          "mean": 1751.0992718167404,
          "ok": 2,
          "shapes": [
            "{\"2\": 1, \"3\": 2, \"4\": 8, \"5\": 4}"
          ],
          "sigs": [
            "b1271e8fb0f6",
            "bb3c54bb5868"
          ],
          "time": 9.024829749999999,
          "worst": 1766.6942664281148
        }
      },
      "official_like": {
        "runs": [
          {
            "cost": 1616.75860162171,
            "cov": 30,
            "shape": {
              "1": 4,
              "2": 22,
              "3": 4
            },
            "sig": "55810f51c401",
            "time": 8.975264417
          },
          {
            "cost": 1616.75860162171,
            "cov": 30,
            "shape": {
              "1": 4,
              "2": 22,
              "3": 4
            },
            "sig": "55810f51c401",
            "time": 9.018755625
          }
        ],
        "summary": {
          "best": 1616.75860162171,
          "cov": [
            30
          ],
          "mean": 1616.75860162171,
          "ok": 2,
          "shapes": [
            "{\"1\": 4, \"2\": 22, \"3\": 4}"
          ],
          "sigs": [
            "55810f51c401"
          ],
          "time": 8.997010021000001,
          "worst": 1616.75860162171
        }
      },
      "scarce40": {
        "runs": [
          {
            "cost": 1097.8470554,
            "cov": 40,
            "shape": {
              "1": 40
            },
            "sig": "2240d8d56f3b",
            "time": 13.111497291000001
          }
        ],
        "summary": {
          "best": 1097.8470554,
          "cov": [
            40
          ],
          "mean": 1097.8470554,
          "ok": 1,
          "shapes": [
            "{\"1\": 40}"
          ],
          "sigs": [
            "2240d8d56f3b"
          ],
          "time": 13.111497291000001,
          "worst": 1097.8470554
        }
      }
    },
    "sha": "77e2ba0b063edfb6f347dd2fe16227243a48e2627a97ef197cbe33d74adbc201",
    "size": 78485
  },
  "rank_willing_only": {
    "cases": {
      "calibrated": {
        "runs": [
          {
            "cost": 1199.1284207596611,
            "cov": 30,
            "shape": {
              "2": 30
            },
            "sig": "0256bf3d47c4",
            "time": 5.058150458
          }
        ],
        "summary": {
          "best": 1199.1284207596611,
          "cov": [
            30
          ],
          "mean": 1199.1284207596611,
          "ok": 1,
          "shapes": [
            "{\"2\": 30}"
          ],
          "sigs": [
            "0256bf3d47c4"
          ],
          "time": 5.058150458,
          "worst": 1199.1284207596611
        }
      },
      "large": {
        "runs": [
          {
            "cost": 657.1040208060375,
            "cov": 40,
            "shape": {
              "1": 3,
              "2": 34,
              "3": 3
            },
            "sig": "bbd61776be78",
            "time": 8.798879958999999
          }
        ],
        "summary": {
          "best": 657.1040208060375,
          "cov": [
            40
          ],
          "mean": 657.1040208060375,
          "ok": 1,
          "shapes": [
            "{\"1\": 3, \"2\": 34, \"3\": 3}"
          ],
          "sigs": [
            "bbd61776be78"
          ],
          "time": 8.798879958999999,
          "worst": 657.1040208060375
        }
      },
      "low025": {
        "runs": [
          {
            "cost": 1891.050799852403,
            "cov": 30,
            "shape": {
              "2": 1,
              "3": 3,
              "4": 6,
              "5": 5
            },
            "sig": "42c828e47d6b",
            "time": 10.067588291
          },
          {
            "cost": 1891.050799852403,
            "cov": 30,
            "shape": {
              "2": 1,
              "3": 3,
              "4": 6,
              "5": 5
            },
            "sig": "42c828e47d6b",
            "time": 9.106205083
          }
        ],
        "summary": {
          "best": 1891.050799852403,
          "cov": [
            30
          ],
          "mean": 1891.050799852403,
          "ok": 2,
          "shapes": [
            "{\"2\": 1, \"3\": 3, \"4\": 6, \"5\": 5}"
          ],
          "sigs": [
            "42c828e47d6b"
          ],
          "time": 9.586896687,
          "worst": 1891.050799852403
        }
      },
      "low030": {
        "runs": [
          {
            "cost": 1760.0074838412038,
            "cov": 30,
            "shape": {
              "3": 4,
              "4": 7,
              "5": 4
            },
            "sig": "2ec04b3dc23b",
            "time": 9.670568500000002
          },
          {
            "cost": 1735.5042772053657,
            "cov": 30,
            "shape": {
              "2": 1,
              "3": 2,
              "4": 8,
              "5": 4
            },
            "sig": "bb3c54bb5868",
            "time": 8.94416475
          }
        ],
        "summary": {
          "best": 1735.5042772053657,
          "cov": [
            30
          ],
          "mean": 1747.7558805232848,
          "ok": 2,
          "shapes": [
            "{\"2\": 1, \"3\": 2, \"4\": 8, \"5\": 4}",
            "{\"3\": 4, \"4\": 7, \"5\": 4}"
          ],
          "sigs": [
            "2ec04b3dc23b",
            "bb3c54bb5868"
          ],
          "time": 9.307366625,
          "worst": 1760.0074838412038
        }
      },
      "official_like": {
        "runs": [
          {
            "cost": 1616.75860162171,
            "cov": 30,
            "shape": {
              "1": 4,
              "2": 22,
              "3": 4
            },
            "sig": "55810f51c401",
            "time": 8.922650084
          },
          {
            "cost": 1616.75860162171,
            "cov": 30,
            "shape": {
              "1": 4,
              "2": 22,
              "3": 4
            },
            "sig": "55810f51c401",
            "time": 8.816196208000001
          }
        ],
        "summary": {
          "best": 1616.75860162171,
          "cov": [
            30
          ],
          "mean": 1616.75860162171,
          "ok": 2,
          "shapes": [
            "{\"1\": 4, \"2\": 22, \"3\": 4}"
          ],
          "sigs": [
            "55810f51c401"
          ],
          "time": 8.869423146,
          "worst": 1616.75860162171
        }
      },
      "scarce40": {
        "runs": [
          {
            "cost": 1097.8470554,
            "cov": 40,
            "shape": {
              "1": 40
            },
            "sig": "2240d8d56f3b",
            "time": 13.24277025
          }
        ],
        "summary": {
          "best": 1097.8470554,
          "cov": [
            40
          ],
          "mean": 1097.8470554,
          "ok": 1,
          "shapes": [
            "{\"1\": 40}"
          ],
          "sigs": [
            "2240d8d56f3b"
          ],
          "time": 13.24277025,
          "worst": 1097.8470554
        }
      }
    },
    "sha": "fff6b995e41d203bce2f927615085f27b2e7fbc767a75735748696c62099574d",
    "size": 78485
  }
}